swarmauri_tool_jupyterruncell/JupyterRunCellTool.py
swarmauri_tool_jupyterruncell/__init__.py
swarmauri_tool_jupyterruncell-0.7.5.dist-info/LICENSE
swarmauri_tool_jupyterruncell-0.7.5.dist-info/METADATA
swarmauri_tool_jupyterruncell-0.7.5.dist-info/WHEEL
swarmauri_tool_jupyterruncell-0.7.5.dist-info/entry_points.txt
swarmauri_tool_jupyterruncell-0.7.5.dist-info/RECORD
